{
  "lastUpdated": "2026-01-15T07:29:34.717Z",
  "twDate": "2026-01-15",
  "stocks": {
    "2880": {
      "id": "2880",
      "name": "華南金",
      "price": 32.9,
      "diff": 0.5,
      "change": 1.54320987654321,
      "isUp": true,
      "category": "官股",
      "pbPercentile": 31,
      "pbValue": 1.01,
      "data": [
        {
          "dateStr": "2026-01-15",
          "time": "09:00",
          "value": 32.45000076293945
        },
        {
          "dateStr": "2026-01-15",
          "time": "09:05",
          "value": 32.650001525878906
        },
        {
          "dateStr": "2026-01-15",
          "time": "09:10",
          "value": 32.650001525878906
        },
        {
          "dateStr": "2026-01-15",
          "time": "09:15",
          "value": 32.70000076293945
        },
        {
          "dateStr": "2026-01-15",
          "time": "09:20",
          "value": 32.70000076293945
        },
        {
          "dateStr": "2026-01-15",
          "time": "09:25",
          "value": 32.75
        },
        {
          "dateStr": "2026-01-15",
          "time": "09:30",
          "value": 32.79999923706055
        },
        {
          "dateStr": "2026-01-15",
          "time": "09:35",
          "value": 32.79999923706055
        },
        {
          "dateStr": "2026-01-15",
          "time": "09:40",
          "value": 32.900001525878906
        },
        {
          "dateStr": "2026-01-15",
          "time": "09:45",
          "value": 32.900001525878906
        },
        {
          "dateStr": "2026-01-15",
          "time": "09:50",
          "value": 32.849998474121094
        },
        {
          "dateStr": "2026-01-15",
          "time": "09:55",
          "value": 32.900001525878906
        },
        {
          "dateStr": "2026-01-15",
          "time": "10:00",
          "value": 33
        },
        {
          "dateStr": "2026-01-15",
          "time": "10:05",
          "value": 32.95000076293945
        },
        {
          "dateStr": "2026-01-15",
          "time": "10:10",
          "value": 32.95000076293945
        },
        {
          "dateStr": "2026-01-15",
          "time": "10:15",
          "value": 32.95000076293945
        },
        {
          "dateStr": "2026-01-15",
          "time": "10:20",
          "value": 32.900001525878906
        },
        {
          "dateStr": "2026-01-15",
          "time": "10:25",
          "value": 32.900001525878906
        },
        {
          "dateStr": "2026-01-15",
          "time": "10:30",
          "value": 32.900001525878906
        },
        {
          "dateStr": "2026-01-15",
          "time": "10:35",
          "value": 32.900001525878906
        },
        {
          "dateStr": "2026-01-15",
          "time": "10:40",
          "value": 32.900001525878906
        },
        {
          "dateStr": "2026-01-15",
          "time": "10:45",
          "value": 32.900001525878906
        },
        {
          "dateStr": "2026-01-15",
          "time": "10:50",
          "value": 32.900001525878906
        },
        {
          "dateStr": "2026-01-15",
          "time": "10:55",
          "value": 32.900001525878906
        },
        {
          "dateStr": "2026-01-15",
          "time": "11:00",
          "value": 32.95000076293945
        },
        {
          "dateStr": "2026-01-15",
          "time": "11:05",
          "value": 32.900001525878906
        },
        {
          "dateStr": "2026-01-15",
          "time": "11:10",
          "value": 32.95000076293945
        },
        {
          "dateStr": "2026-01-15",
          "time": "11:15",
          "value": 32.95000076293945
        },
        {
          "dateStr": "2026-01-15",
          "time": "11:20",
          "value": 32.95000076293945
        },
        {
          "dateStr": "2026-01-15",
          "time": "11:25",
          "value": 32.95000076293945
        },
        {
          "dateStr": "2026-01-15",
          "time": "11:30",
          "value": 33
        },
        {
          "dateStr": "2026-01-15",
          "time": "11:35",
          "value": 33
        },
        {
          "dateStr": "2026-01-15",
          "time": "11:40",
          "value": 32.95000076293945
        },
        {
          "dateStr": "2026-01-15",
          "time": "11:45",
          "value": 33
        },
        {
          "dateStr": "2026-01-15",
          "time": "11:50",
          "value": 32.95000076293945
        },
        {
          "dateStr": "2026-01-15",
          "time": "11:55",
          "value": 32.900001525878906
        },
        {
          "dateStr": "2026-01-15",
          "time": "12:00",
          "value": 32.95000076293945
        },
        {
          "dateStr": "2026-01-15",
          "time": "12:05",
          "value": 32.95000076293945
        },
        {
          "dateStr": "2026-01-15",
          "time": "12:10",
          "value": 32.900001525878906
        },
        {
          "dateStr": "2026-01-15",
          "time": "12:15",
          "value": 32.849998474121094
        },
        {
          "dateStr": "2026-01-15",
          "time": "12:20",
          "value": 32.849998474121094
        },
        {
          "dateStr": "2026-01-15",
          "time": "12:25",
          "value": 32.95000076293945
        },
        {
          "dateStr": "2026-01-15",
          "time": "12:30",
          "value": 32.95000076293945
        },
        {
          "dateStr": "2026-01-15",
          "time": "12:35",
          "value": 32.849998474121094
        },
        {
          "dateStr": "2026-01-15",
          "time": "12:40",
          "value": 32.95000076293945
        },
        {
          "dateStr": "2026-01-15",
          "time": "12:45",
          "value": 32.900001525878906
        },
        {
          "dateStr": "2026-01-15",
          "time": "12:50",
          "value": 32.95000076293945
        },
        {
          "dateStr": "2026-01-15",
          "time": "12:55",
          "value": 32.900001525878906
        },
        {
          "dateStr": "2026-01-15",
          "time": "13:00",
          "value": 32.95000076293945
        },
        {
          "dateStr": "2026-01-15",
          "time": "13:05",
          "value": 32.95000076293945
        },
        {
          "dateStr": "2026-01-15",
          "time": "13:10",
          "value": 32.95000076293945
        },
        {
          "dateStr": "2026-01-15",
          "time": "13:15",
          "value": 32.900001525878906
        },
        {
          "dateStr": "2026-01-15",
          "time": "13:20",
          "value": 32.849998474121094
        },
        {
          "dateStr": "2026-01-15",
          "time": "13:30",
          "value": 32.900001525878906
        }
      ]
    },
    "2881": {
      "id": "2881",
      "name": "富邦金",
      "price": 94.1,
      "diff": 0.29999999999999716,
      "change": 0.3198294243070332,
      "isUp": true,
      "category": "民營",
      "pbPercentile": 100,
      "pbValue": 3.02,
      "data": [
        {
          "dateStr": "2026-01-15",
          "time": "09:00",
          "value": 94.9000015258789
        },
        {
          "dateStr": "2026-01-15",
          "time": "09:05",
          "value": 95.19999694824219
        },
        {
          "dateStr": "2026-01-15",
          "time": "09:10",
          "value": 95.30000305175781
        },
        {
          "dateStr": "2026-01-15",
          "time": "09:15",
          "value": 95.19999694824219
        },
        {
          "dateStr": "2026-01-15",
          "time": "09:20",
          "value": 95.0999984741211
        },
        {
          "dateStr": "2026-01-15",
          "time": "09:25",
          "value": 94.9000015258789
        },
        {
          "dateStr": "2026-01-15",
          "time": "09:30",
          "value": 95
        },
        {
          "dateStr": "2026-01-15",
          "time": "09:35",
          "value": 95.0999984741211
        },
        {
          "dateStr": "2026-01-15",
          "time": "09:40",
          "value": 95.30000305175781
        },
        {
          "dateStr": "2026-01-15",
          "time": "09:45",
          "value": 95.30000305175781
        },
        {
          "dateStr": "2026-01-15",
          "time": "09:50",
          "value": 95.30000305175781
        },
        {
          "dateStr": "2026-01-15",
          "time": "09:55",
          "value": 95.5
        },
        {
          "dateStr": "2026-01-15",
          "time": "10:00",
          "value": 95.4000015258789
        },
        {
          "dateStr": "2026-01-15",
          "time": "10:05",
          "value": 95.30000305175781
        },
        {
          "dateStr": "2026-01-15",
          "time": "10:10",
          "value": 95
        },
        {
          "dateStr": "2026-01-15",
          "time": "10:15",
          "value": 95
        },
        {
          "dateStr": "2026-01-15",
          "time": "10:20",
          "value": 95
        },
        {
          "dateStr": "2026-01-15",
          "time": "10:25",
          "value": 94.9000015258789
        },
        {
          "dateStr": "2026-01-15",
          "time": "10:30",
          "value": 95
        },
        {
          "dateStr": "2026-01-15",
          "time": "10:35",
          "value": 94.9000015258789
        },
        {
          "dateStr": "2026-01-15",
          "time": "10:40",
          "value": 94.9000015258789
        },
        {
          "dateStr": "2026-01-15",
          "time": "10:45",
          "value": 94.80000305175781
        },
        {
          "dateStr": "2026-01-15",
          "time": "10:50",
          "value": 94.9000015258789
        },
        {
          "dateStr": "2026-01-15",
          "time": "10:55",
          "value": 94.69999694824219
        },
        {
          "dateStr": "2026-01-15",
          "time": "11:00",
          "value": 94.5999984741211
        },
        {
          "dateStr": "2026-01-15",
          "time": "11:05",
          "value": 94.5999984741211
        },
        {
          "dateStr": "2026-01-15",
          "time": "11:10",
          "value": 94.5999984741211
        },
        {
          "dateStr": "2026-01-15",
          "time": "11:15",
          "value": 94.5999984741211
        },
        {
          "dateStr": "2026-01-15",
          "time": "11:20",
          "value": 94.5
        },
        {
          "dateStr": "2026-01-15",
          "time": "11:25",
          "value": 94.80000305175781
        },
        {
          "dateStr": "2026-01-15",
          "time": "11:30",
          "value": 94.69999694824219
        },
        {
          "dateStr": "2026-01-15",
          "time": "11:35",
          "value": 94.5999984741211
        },
        {
          "dateStr": "2026-01-15",
          "time": "11:40",
          "value": 94.69999694824219
        },
        {
          "dateStr": "2026-01-15",
          "time": "11:45",
          "value": 94.5
        },
        {
          "dateStr": "2026-01-15",
          "time": "11:50",
          "value": 94.5999984741211
        },
        {
          "dateStr": "2026-01-15",
          "time": "11:55",
          "value": 94.5
        },
        {
          "dateStr": "2026-01-15",
          "time": "12:00",
          "value": 94.5
        },
        {
          "dateStr": "2026-01-15",
          "time": "12:05",
          "value": 94.5
        },
        {
          "dateStr": "2026-01-15",
          "time": "12:10",
          "value": 94.5999984741211
        },
        {
          "dateStr": "2026-01-15",
          "time": "12:15",
          "value": 94.5999984741211
        },
        {
          "dateStr": "2026-01-15",
          "time": "12:20",
          "value": 94.5999984741211
        },
        {
          "dateStr": "2026-01-15",
          "time": "12:25",
          "value": 94.80000305175781
        },
        {
          "dateStr": "2026-01-15",
          "time": "12:30",
          "value": 94.5999984741211
        },
        {
          "dateStr": "2026-01-15",
          "time": "12:35",
          "value": 94.19999694824219
        },
        {
          "dateStr": "2026-01-15",
          "time": "12:40",
          "value": 94.19999694824219
        },
        {
          "dateStr": "2026-01-15",
          "time": "12:45",
          "value": 94.19999694824219
        },
        {
          "dateStr": "2026-01-15",
          "time": "12:50",
          "value": 94.30000305175781
        },
        {
          "dateStr": "2026-01-15",
          "time": "12:55",
          "value": 94.0999984741211
        },
        {
          "dateStr": "2026-01-15",
          "time": "13:00",
          "value": 94.19999694824219
        },
        {
          "dateStr": "2026-01-15",
          "time": "13:05",
          "value": 94.4000015258789
        },
        {
          "dateStr": "2026-01-15",
          "time": "13:10",
          "value": 94.30000305175781
        },
        {
          "dateStr": "2026-01-15",
          "time": "13:15",
          "value": 94.19999694824219
        },
        {
          "dateStr": "2026-01-15",
          "time": "13:20",
          "value": 94.0999984741211
        },
        {
          "dateStr": "2026-01-15",
          "time": "13:30",
          "value": 94.0999984741211
        }
      ]
    },
    "2882": {
      "id": "2882",
      "name": "國泰金",
      "price": 75.2,
      "diff": 0.5,
      "change": 0.6693440428380187,
      "isUp": true,
      "category": "民營",
      "pbPercentile": 94,
      "pbValue": 2.61,
      "data": [
        {
          "dateStr": "2026-01-15",
          "time": "09:00",
          "value": 75.5
        },
        {
          "dateStr": "2026-01-15",
          "time": "09:05",
          "value": 75.80000305175781
        },
        {
          "dateStr": "2026-01-15",
          "time": "09:10",
          "value": 75.80000305175781
        },
        {
          "dateStr": "2026-01-15",
          "time": "09:15",
          "value": 75.5999984741211
        },
        {
          "dateStr": "2026-01-15",
          "time": "09:20",
          "value": 75.4000015258789
        },
        {
          "dateStr": "2026-01-15",
          "time": "09:25",
          "value": 75.5999984741211
        },
        {
          "dateStr": "2026-01-15",
          "time": "09:30",
          "value": 75.5
        },
        {
          "dateStr": "2026-01-15",
          "time": "09:35",
          "value": 75.5
        },
        {
          "dateStr": "2026-01-15",
          "time": "09:40",
          "value": 75.80000305175781
        },
        {
          "dateStr": "2026-01-15",
          "time": "09:45",
          "value": 75.80000305175781
        },
        {
          "dateStr": "2026-01-15",
          "time": "09:50",
          "value": 75.69999694824219
        },
        {
          "dateStr": "2026-01-15",
          "time": "09:55",
          "value": 75.80000305175781
        },
        {
          "dateStr": "2026-01-15",
          "time": "10:00",
          "value": 75.80000305175781
        },
        {
          "dateStr": "2026-01-15",
          "time": "10:05",
          "value": 75.5999984741211
        },
        {
          "dateStr": "2026-01-15",
          "time": "10:10",
          "value": 75.5999984741211
        },
        {
          "dateStr": "2026-01-15",
          "time": "10:15",
          "value": 75.5999984741211
        },
        {
          "dateStr": "2026-01-15",
          "time": "10:20",
          "value": 75.5999984741211
        },
        {
          "dateStr": "2026-01-15",
          "time": "10:25",
          "value": 75.5999984741211
        },
        {
          "dateStr": "2026-01-15",
          "time": "10:30",
          "value": 75.69999694824219
        },
        {
          "dateStr": "2026-01-15",
          "time": "10:35",
          "value": 75.69999694824219
        },
        {
          "dateStr": "2026-01-15",
          "time": "10:40",
          "value": 75.69999694824219
        },
        {
          "dateStr": "2026-01-15",
          "time": "10:45",
          "value": 75.5
        },
        {
          "dateStr": "2026-01-15",
          "time": "10:50",
          "value": 75.4000015258789
        },
        {
          "dateStr": "2026-01-15",
          "time": "10:55",
          "value": 75.4000015258789
        },
        {
          "dateStr": "2026-01-15",
          "time": "11:00",
          "value": 75.4000015258789
        },
        {
          "dateStr": "2026-01-15",
          "time": "11:05",
          "value": 75.30000305175781
        },
        {
          "dateStr": "2026-01-15",
          "time": "11:10",
          "value": 75.4000015258789
        },
        {
          "dateStr": "2026-01-15",
          "time": "11:15",
          "value": 75.5
        },
        {
          "dateStr": "2026-01-15",
          "time": "11:20",
          "value": 75.5999984741211
        },
        {
          "dateStr": "2026-01-15",
          "time": "11:25",
          "value": 75.69999694824219
        },
        {
          "dateStr": "2026-01-15",
          "time": "11:30",
          "value": 75.5999984741211
        },
        {
          "dateStr": "2026-01-15",
          "time": "11:35",
          "value": 75.69999694824219
        },
        {
          "dateStr": "2026-01-15",
          "time": "11:40",
          "value": 75.4000015258789
        },
        {
          "dateStr": "2026-01-15",
          "time": "11:45",
          "value": 75.4000015258789
        },
        {
          "dateStr": "2026-01-15",
          "time": "11:50",
          "value": 75.4000015258789
        },
        {
          "dateStr": "2026-01-15",
          "time": "11:55",
          "value": 75.4000015258789
        },
        {
          "dateStr": "2026-01-15",
          "time": "12:00",
          "value": 75.5
        },
        {
          "dateStr": "2026-01-15",
          "time": "12:05",
          "value": 75.4000015258789
        },
        {
          "dateStr": "2026-01-15",
          "time": "12:10",
          "value": 75.4000015258789
        },
        {
          "dateStr": "2026-01-15",
          "time": "12:15",
          "value": 75.4000015258789
        },
        {
          "dateStr": "2026-01-15",
          "time": "12:20",
          "value": 75.5
        },
        {
          "dateStr": "2026-01-15",
          "time": "12:25",
          "value": 75.69999694824219
        },
        {
          "dateStr": "2026-01-15",
          "time": "12:30",
          "value": 75.5
        },
        {
          "dateStr": "2026-01-15",
          "time": "12:35",
          "value": 75.4000015258789
        },
        {
          "dateStr": "2026-01-15",
          "time": "12:40",
          "value": 75.4000015258789
        },
        {
          "dateStr": "2026-01-15",
          "time": "12:45",
          "value": 75.4000015258789
        },
        {
          "dateStr": "2026-01-15",
          "time": "12:50",
          "value": 75.4000015258789
        },
        {
          "dateStr": "2026-01-15",
          "time": "12:55",
          "value": 75.4000015258789
        },
        {
          "dateStr": "2026-01-15",
          "time": "13:00",
          "value": 75.4000015258789
        },
        {
          "dateStr": "2026-01-15",
          "time": "13:05",
          "value": 75.4000015258789
        },
        {
          "dateStr": "2026-01-15",
          "time": "13:10",
          "value": 75.30000305175781
        },
        {
          "dateStr": "2026-01-15",
          "time": "13:15",
          "value": 75.30000305175781
        },
        {
          "dateStr": "2026-01-15",
          "time": "13:20",
          "value": 75.4000015258789
        },
        {
          "dateStr": "2026-01-15",
          "time": "13:30",
          "value": 75.19999694824219
        }
      ]
    },
    "2883": {
      "id": "2883",
      "name": "凱基金",
      "price": 17.55,
      "diff": 0.05000000000000071,
      "change": 0.2857142857142898,
      "isUp": true,
      "category": "民營",
      "pbPercentile": 28,
      "pbValue": 0.95,
      "data": [
        {
          "dateStr": "2026-01-15",
          "time": "09:00",
          "value": 17.600000381469727
        },
        {
          "dateStr": "2026-01-15",
          "time": "09:05",
          "value": 17.649999618530273
        },
        {
          "dateStr": "2026-01-15",
          "time": "09:10",
          "value": 17.75
        },
        {
          "dateStr": "2026-01-15",
          "time": "09:15",
          "value": 17.700000762939453
        },
        {
          "dateStr": "2026-01-15",
          "time": "09:20",
          "value": 17.700000762939453
        },
        {
          "dateStr": "2026-01-15",
          "time": "09:25",
          "value": 17.700000762939453
        },
        {
          "dateStr": "2026-01-15",
          "time": "09:30",
          "value": 17.700000762939453
        },
        {
          "dateStr": "2026-01-15",
          "time": "09:35",
          "value": 17.649999618530273
        },
        {
          "dateStr": "2026-01-15",
          "time": "09:40",
          "value": 17.75
        },
        {
          "dateStr": "2026-01-15",
          "time": "09:45",
          "value": 17.75
        },
        {
          "dateStr": "2026-01-15",
          "time": "09:50",
          "value": 17.700000762939453
        },
        {
          "dateStr": "2026-01-15",
          "time": "09:55",
          "value": 17.700000762939453
        },
        {
          "dateStr": "2026-01-15",
          "time": "10:00",
          "value": 17.75
        },
        {
          "dateStr": "2026-01-15",
          "time": "10:05",
          "value": 17.700000762939453
        },
        {
          "dateStr": "2026-01-15",
          "time": "10:10",
          "value": 17.700000762939453
        },
        {
          "dateStr": "2026-01-15",
          "time": "10:15",
          "value": 17.700000762939453
        },
        {
          "dateStr": "2026-01-15",
          "time": "10:20",
          "value": 17.700000762939453
        },
        {
          "dateStr": "2026-01-15",
          "time": "10:25",
          "value": 17.649999618530273
        },
        {
          "dateStr": "2026-01-15",
          "time": "10:30",
          "value": 17.700000762939453
        },
        {
          "dateStr": "2026-01-15",
          "time": "10:35",
          "value": 17.700000762939453
        },
        {
          "dateStr": "2026-01-15",
          "time": "10:40",
          "value": 17.649999618530273
        },
        {
          "dateStr": "2026-01-15",
          "time": "10:45",
          "value": 17.700000762939453
        },
        {
          "dateStr": "2026-01-15",
          "time": "10:50",
          "value": 17.700000762939453
        },
        {
          "dateStr": "2026-01-15",
          "time": "10:55",
          "value": 17.700000762939453
        },
        {
          "dateStr": "2026-01-15",
          "time": "11:00",
          "value": 17.700000762939453
        },
        {
          "dateStr": "2026-01-15",
          "time": "11:05",
          "value": 17.700000762939453
        },
        {
          "dateStr": "2026-01-15",
          "time": "11:10",
          "value": 17.700000762939453
        },
        {
          "dateStr": "2026-01-15",
          "time": "11:15",
          "value": 17.649999618530273
        },
        {
          "dateStr": "2026-01-15",
          "time": "11:20",
          "value": 17.700000762939453
        },
        {
          "dateStr": "2026-01-15",
          "time": "11:25",
          "value": 17.700000762939453
        },
        {
          "dateStr": "2026-01-15",
          "time": "11:30",
          "value": 17.700000762939453
        },
        {
          "dateStr": "2026-01-15",
          "time": "11:35",
          "value": 17.649999618530273
        },
        {
          "dateStr": "2026-01-15",
          "time": "11:40",
          "value": 17.649999618530273
        },
        {
          "dateStr": "2026-01-15",
          "time": "11:45",
          "value": 17.700000762939453
        },
        {
          "dateStr": "2026-01-15",
          "time": "11:50",
          "value": 17.649999618530273
        },
        {
          "dateStr": "2026-01-15",
          "time": "11:55",
          "value": 17.600000381469727
        },
        {
          "dateStr": "2026-01-15",
          "time": "12:00",
          "value": 17.600000381469727
        },
        {
          "dateStr": "2026-01-15",
          "time": "12:05",
          "value": 17.600000381469727
        },
        {
          "dateStr": "2026-01-15",
          "time": "12:10",
          "value": 17.649999618530273
        },
        {
          "dateStr": "2026-01-15",
          "time": "12:15",
          "value": 17.600000381469727
        },
        {
          "dateStr": "2026-01-15",
          "time": "12:20",
          "value": 17.649999618530273
        },
        {
          "dateStr": "2026-01-15",
          "time": "12:25",
          "value": 17.649999618530273
        },
        {
          "dateStr": "2026-01-15",
          "time": "12:30",
          "value": 17.649999618530273
        },
        {
          "dateStr": "2026-01-15",
          "time": "12:35",
          "value": 17.649999618530273
        },
        {
          "dateStr": "2026-01-15",
          "time": "12:40",
          "value": 17.649999618530273
        },
        {
          "dateStr": "2026-01-15",
          "time": "12:45",
          "value": 17.600000381469727
        },
        {
          "dateStr": "2026-01-15",
          "time": "12:50",
          "value": 17.600000381469727
        },
        {
          "dateStr": "2026-01-15",
          "time": "12:55",
          "value": 17.600000381469727
        },
        {
          "dateStr": "2026-01-15",
          "time": "13:00",
          "value": 17.649999618530273
        },
        {
          "dateStr": "2026-01-15",
          "time": "13:05",
          "value": 17.649999618530273
        },
        {
          "dateStr": "2026-01-15",
          "time": "13:10",
          "value": 17.600000381469727
        },
        {
          "dateStr": "2026-01-15",
          "time": "13:15",
          "value": 17.649999618530273
        },
        {
          "dateStr": "2026-01-15",
          "time": "13:20",
          "value": 17.600000381469727
        },
        {
          "dateStr": "2026-01-15",
          "time": "13:30",
          "value": 17.549999237060547
        }
      ]
    },
    "2884": {
      "id": "2884",
      "name": "玉山金",
      "price": 32.45,
      "diff": 0.15000000000000568,
      "change": 0.46439628482973905,
      "isUp": true,
      "category": "民營",
      "pbPercentile": 93,
      "pbValue": 2.54,
      "data": [
        {
          "dateStr": "2026-01-15",
          "time": "09:00",
          "value": 32.45000076293945
        },
        {
          "dateStr": "2026-01-15",
          "time": "09:05",
          "value": 32.599998474121094
        },
        {
          "dateStr": "2026-01-15",
          "time": "09:10",
          "value": 32.650001525878906
        },
        {
          "dateStr": "2026-01-15",
          "time": "09:15",
          "value": 32.70000076293945
        },
        {
          "dateStr": "2026-01-15",
          "time": "09:20",
          "value": 32.54999923706055
        },
        {
          "dateStr": "2026-01-15",
          "time": "09:25",
          "value": 32.54999923706055
        },
        {
          "dateStr": "2026-01-15",
          "time": "09:30",
          "value": 32.54999923706055
        },
        {
          "dateStr": "2026-01-15",
          "time": "09:35",
          "value": 32.54999923706055
        },
        {
          "dateStr": "2026-01-15",
          "time": "09:40",
          "value": 32.650001525878906
        },
        {
          "dateStr": "2026-01-15",
          "time": "09:45",
          "value": 32.650001525878906
        },
        {
          "dateStr": "2026-01-15",
          "time": "09:50",
          "value": 32.599998474121094
        },
        {
          "dateStr": "2026-01-15",
          "time": "09:55",
          "value": 32.650001525878906
        },
        {
          "dateStr": "2026-01-15",
          "time": "10:00",
          "value": 32.650001525878906
        },
        {
          "dateStr": "2026-01-15",
          "time": "10:05",
          "value": 32.599998474121094
        },
        {
          "dateStr": "2026-01-15",
          "time": "10:10",
          "value": 32.599998474121094
        },
        {
          "dateStr": "2026-01-15",
          "time": "10:15",
          "value": 32.599998474121094
        },
        {
          "dateStr": "2026-01-15",
          "time": "10:20",
          "value": 32.54999923706055
        },
        {
          "dateStr": "2026-01-15",
          "time": "10:25",
          "value": 32.54999923706055
        },
        {
          "dateStr": "2026-01-15",
          "time": "10:30",
          "value": 32.54999923706055
        },
        {
          "dateStr": "2026-01-15",
          "time": "10:35",
          "value": 32.5
        },
        {
          "dateStr": "2026-01-15",
          "time": "10:40",
          "value": 32.5
        },
        {
          "dateStr": "2026-01-15",
          "time": "10:45",
          "value": 32.5
        },
        {
          "dateStr": "2026-01-15",
          "time": "10:50",
          "value": 32.5
        },
        {
          "dateStr": "2026-01-15",
          "time": "10:55",
          "value": 32.54999923706055
        },
        {
          "dateStr": "2026-01-15",
          "time": "11:00",
          "value": 32.54999923706055
        },
        {
          "dateStr": "2026-01-15",
          "time": "11:05",
          "value": 32.650001525878906
        },
        {
          "dateStr": "2026-01-15",
          "time": "11:10",
          "value": 32.599998474121094
        },
        {
          "dateStr": "2026-01-15",
          "time": "11:15",
          "value": 32.599998474121094
        },
        {
          "dateStr": "2026-01-15",
          "time": "11:20",
          "value": 32.650001525878906
        },
        {
          "dateStr": "2026-01-15",
          "time": "11:25",
          "value": 32.599998474121094
        },
        {
          "dateStr": "2026-01-15",
          "time": "11:30",
          "value": 32.599998474121094
        },
        {
          "dateStr": "2026-01-15",
          "time": "11:35",
          "value": 32.599998474121094
        },
        {
          "dateStr": "2026-01-15",
          "time": "11:40",
          "value": 32.54999923706055
        },
        {
          "dateStr": "2026-01-15",
          "time": "11:45",
          "value": 32.54999923706055
        },
        {
          "dateStr": "2026-01-15",
          "time": "11:50",
          "value": 32.599998474121094
        },
        {
          "dateStr": "2026-01-15",
          "time": "11:55",
          "value": 32.54999923706055
        },
        {
          "dateStr": "2026-01-15",
          "time": "12:00",
          "value": 32.54999923706055
        },
        {
          "dateStr": "2026-01-15",
          "time": "12:05",
          "value": 32.54999923706055
        },
        {
          "dateStr": "2026-01-15",
          "time": "12:10",
          "value": 32.54999923706055
        },
        {
          "dateStr": "2026-01-15",
          "time": "12:15",
          "value": 32.54999923706055
        },
        {
          "dateStr": "2026-01-15",
          "time": "12:20",
          "value": 32.599998474121094
        },
        {
          "dateStr": "2026-01-15",
          "time": "12:25",
          "value": 32.54999923706055
        },
        {
          "dateStr": "2026-01-15",
          "time": "12:30",
          "value": 32.54999923706055
        },
        {
          "dateStr": "2026-01-15",
          "time": "12:35",
          "value": 32.54999923706055
        },
        {
          "dateStr": "2026-01-15",
          "time": "12:40",
          "value": 32.54999923706055
        },
        {
          "dateStr": "2026-01-15",
          "time": "12:45",
          "value": 32.54999923706055
        },
        {
          "dateStr": "2026-01-15",
          "time": "12:50",
          "value": 32.54999923706055
        },
        {
          "dateStr": "2026-01-15",
          "time": "12:55",
          "value": 32.54999923706055
        },
        {
          "dateStr": "2026-01-15",
          "time": "13:00",
          "value": 32.54999923706055
        },
        {
          "dateStr": "2026-01-15",
          "time": "13:05",
          "value": 32.5
        },
        {
          "dateStr": "2026-01-15",
          "time": "13:10",
          "value": 32.5
        },
        {
          "dateStr": "2026-01-15",
          "time": "13:15",
          "value": 32.5
        },
        {
          "dateStr": "2026-01-15",
          "time": "13:20",
          "value": 32.54999923706055
        },
        {
          "dateStr": "2026-01-15",
          "time": "13:30",
          "value": 32.45000076293945
        }
      ]
    },
    "2885": {
      "id": "2885",
      "name": "元大金",
      "price": 41.85,
      "diff": 0.7000000000000028,
      "change": 1.7010935601458148,
      "isUp": true,
      "category": "民營",
      "pbPercentile": 96,
      "pbValue": 2.75,
      "data": [
        {
          "dateStr": "2026-01-15",
          "time": "09:00",
          "value": 41.45000076293945
        },
        {
          "dateStr": "2026-01-15",
          "time": "09:05",
          "value": 41.45000076293945
        },
        {
          "dateStr": "2026-01-15",
          "time": "09:10",
          "value": 41.70000076293945
        },
        {
          "dateStr": "2026-01-15",
          "time": "09:15",
          "value": 41.70000076293945
        },
        {
          "dateStr": "2026-01-15",
          "time": "09:20",
          "value": 41.75
        },
        {
          "dateStr": "2026-01-15",
          "time": "09:25",
          "value": 41.650001525878906
        },
        {
          "dateStr": "2026-01-15",
          "time": "09:30",
          "value": 41.650001525878906
        },
        {
          "dateStr": "2026-01-15",
          "time": "09:35",
          "value": 41.54999923706055
        },
        {
          "dateStr": "2026-01-15",
          "time": "09:40",
          "value": 41.849998474121094
        },
        {
          "dateStr": "2026-01-15",
          "time": "09:45",
          "value": 42.04999923706055
        },
        {
          "dateStr": "2026-01-15",
          "time": "09:50",
          "value": 41.95000076293945
        },
        {
          "dateStr": "2026-01-15",
          "time": "09:55",
          "value": 42
        },
        {
          "dateStr": "2026-01-15",
          "time": "10:00",
          "value": 42.099998474121094
        },
        {
          "dateStr": "2026-01-15",
          "time": "10:05",
          "value": 42.04999923706055
        },
        {
          "dateStr": "2026-01-15",
          "time": "10:10",
          "value": 41.900001525878906
        },
        {
          "dateStr": "2026-01-15",
          "time": "10:15",
          "value": 42
        },
        {
          "dateStr": "2026-01-15",
          "time": "10:20",
          "value": 42.04999923706055
        },
        {
          "dateStr": "2026-01-15",
          "time": "10:25",
          "value": 42.04999923706055
        },
        {
          "dateStr": "2026-01-15",
          "time": "10:30",
          "value": 42
        },
        {
          "dateStr": "2026-01-15",
          "time": "10:35",
          "value": 41.95000076293945
        },
        {
          "dateStr": "2026-01-15",
          "time": "10:40",
          "value": 42
        },
        {
          "dateStr": "2026-01-15",
          "time": "10:45",
          "value": 42
        },
        {
          "dateStr": "2026-01-15",
          "time": "10:50",
          "value": 41.95000076293945
        },
        {
          "dateStr": "2026-01-15",
          "time": "10:55",
          "value": 41.79999923706055
        },
        {
          "dateStr": "2026-01-15",
          "time": "11:00",
          "value": 41.95000076293945
        },
        {
          "dateStr": "2026-01-15",
          "time": "11:05",
          "value": 41.95000076293945
        },
        {
          "dateStr": "2026-01-15",
          "time": "11:10",
          "value": 41.95000076293945
        },
        {
          "dateStr": "2026-01-15",
          "time": "11:15",
          "value": 42
        },
        {
          "dateStr": "2026-01-15",
          "time": "11:20",
          "value": 41.95000076293945
        },
        {
          "dateStr": "2026-01-15",
          "time": "11:25",
          "value": 42.04999923706055
        },
        {
          "dateStr": "2026-01-15",
          "time": "11:30",
          "value": 42.099998474121094
        },
        {
          "dateStr": "2026-01-15",
          "time": "11:35",
          "value": 42.150001525878906
        },
        {
          "dateStr": "2026-01-15",
          "time": "11:40",
          "value": 42.150001525878906
        },
        {
          "dateStr": "2026-01-15",
          "time": "11:45",
          "value": 42.150001525878906
        },
        {
          "dateStr": "2026-01-15",
          "time": "11:50",
          "value": 42.099998474121094
        },
        {
          "dateStr": "2026-01-15",
          "time": "11:55",
          "value": 42.099998474121094
        },
        {
          "dateStr": "2026-01-15",
          "time": "12:00",
          "value": 42.150001525878906
        },
        {
          "dateStr": "2026-01-15",
          "time": "12:05",
          "value": 42.20000076293945
        },
        {
          "dateStr": "2026-01-15",
          "time": "12:10",
          "value": 42.099998474121094
        },
        {
          "dateStr": "2026-01-15",
          "time": "12:15",
          "value": 42
        },
        {
          "dateStr": "2026-01-15",
          "time": "12:20",
          "value": 42.099998474121094
        },
        {
          "dateStr": "2026-01-15",
          "time": "12:25",
          "value": 42.150001525878906
        },
        {
          "dateStr": "2026-01-15",
          "time": "12:30",
          "value": 42.04999923706055
        },
        {
          "dateStr": "2026-01-15",
          "time": "12:35",
          "value": 41.900001525878906
        },
        {
          "dateStr": "2026-01-15",
          "time": "12:40",
          "value": 41.900001525878906
        },
        {
          "dateStr": "2026-01-15",
          "time": "12:45",
          "value": 41.95000076293945
        },
        {
          "dateStr": "2026-01-15",
          "time": "12:50",
          "value": 41.900001525878906
        },
        {
          "dateStr": "2026-01-15",
          "time": "12:55",
          "value": 41.95000076293945
        },
        {
          "dateStr": "2026-01-15",
          "time": "13:00",
          "value": 41.79999923706055
        },
        {
          "dateStr": "2026-01-15",
          "time": "13:05",
          "value": 41.900001525878906
        },
        {
          "dateStr": "2026-01-15",
          "time": "13:10",
          "value": 41.849998474121094
        },
        {
          "dateStr": "2026-01-15",
          "time": "13:15",
          "value": 41.849998474121094
        },
        {
          "dateStr": "2026-01-15",
          "time": "13:20",
          "value": 41.95000076293945
        },
        {
          "dateStr": "2026-01-15",
          "time": "13:30",
          "value": 41.849998474121094
        }
      ]
    },
    "2886": {
      "id": "2886",
      "name": "兆豐金",
      "price": 40.65,
      "diff": 0.14999999999999858,
      "change": 0.37037037037036685,
      "isUp": true,
      "category": "官股",
      "pbPercentile": 87,
      "pbValue": 2.15,
      "data": [
        {
          "dateStr": "2026-01-15",
          "time": "09:00",
          "value": 40.54999923706055
        },
        {
          "dateStr": "2026-01-15",
          "time": "09:05",
          "value": 40.599998474121094
        },
        {
          "dateStr": "2026-01-15",
          "time": "09:10",
          "value": 40.650001525878906
        },
        {
          "dateStr": "2026-01-15",
          "time": "09:15",
          "value": 40.54999923706055
        },
        {
          "dateStr": "2026-01-15",
          "time": "09:20",
          "value": 40.650001525878906
        },
        {
          "dateStr": "2026-01-15",
          "time": "09:25",
          "value": 40.599998474121094
        },
        {
          "dateStr": "2026-01-15",
          "time": "09:30",
          "value": 40.650001525878906
        },
        {
          "dateStr": "2026-01-15",
          "time": "09:35",
          "value": 40.54999923706055
        },
        {
          "dateStr": "2026-01-15",
          "time": "09:40",
          "value": 40.650001525878906
        },
        {
          "dateStr": "2026-01-15",
          "time": "09:45",
          "value": 40.650001525878906
        },
        {
          "dateStr": "2026-01-15",
          "time": "09:50",
          "value": 40.650001525878906
        },
        {
          "dateStr": "2026-01-15",
          "time": "09:55",
          "value": 40.70000076293945
        },
        {
          "dateStr": "2026-01-15",
          "time": "10:00",
          "value": 40.70000076293945
        },
        {
          "dateStr": "2026-01-15",
          "time": "10:05",
          "value": 40.70000076293945
        },
        {
          "dateStr": "2026-01-15",
          "time": "10:10",
          "value": 40.70000076293945
        },
        {
          "dateStr": "2026-01-15",
          "time": "10:15",
          "value": 40.650001525878906
        },
        {
          "dateStr": "2026-01-15",
          "time": "10:20",
          "value": 40.650001525878906
        },
        {
          "dateStr": "2026-01-15",
          "time": "10:25",
          "value": 40.650001525878906
        },
        {
          "dateStr": "2026-01-15",
          "time": "10:30",
          "value": 40.70000076293945
        },
        {
          "dateStr": "2026-01-15",
          "time": "10:35",
          "value": 40.70000076293945
        },
        {
          "dateStr": "2026-01-15",
          "time": "10:40",
          "value": 40.650001525878906
        },
        {
          "dateStr": "2026-01-15",
          "time": "10:45",
          "value": 40.650001525878906
        },
        {
          "dateStr": "2026-01-15",
          "time": "10:50",
          "value": 40.650001525878906
        },
        {
          "dateStr": "2026-01-15",
          "time": "10:55",
          "value": 40.70000076293945
        },
        {
          "dateStr": "2026-01-15",
          "time": "11:00",
          "value": 40.650001525878906
        },
        {
          "dateStr": "2026-01-15",
          "time": "11:05",
          "value": 40.70000076293945
        },
        {
          "dateStr": "2026-01-15",
          "time": "11:10",
          "value": 40.650001525878906
        },
        {
          "dateStr": "2026-01-15",
          "time": "11:15",
          "value": 40.650001525878906
        },
        {
          "dateStr": "2026-01-15",
          "time": "11:20",
          "value": 40.70000076293945
        },
        {
          "dateStr": "2026-01-15",
          "time": "11:25",
          "value": 40.650001525878906
        },
        {
          "dateStr": "2026-01-15",
          "time": "11:30",
          "value": 40.650001525878906
        },
        {
          "dateStr": "2026-01-15",
          "time": "11:35",
          "value": 40.650001525878906
        },
        {
          "dateStr": "2026-01-15",
          "time": "11:40",
          "value": 40.650001525878906
        },
        {
          "dateStr": "2026-01-15",
          "time": "11:45",
          "value": 40.599998474121094
        },
        {
          "dateStr": "2026-01-15",
          "time": "11:50",
          "value": 40.599998474121094
        },
        {
          "dateStr": "2026-01-15",
          "time": "11:55",
          "value": 40.599998474121094
        },
        {
          "dateStr": "2026-01-15",
          "time": "12:00",
          "value": 40.599998474121094
        },
        {
          "dateStr": "2026-01-15",
          "time": "12:05",
          "value": 40.599998474121094
        },
        {
          "dateStr": "2026-01-15",
          "time": "12:10",
          "value": 40.599998474121094
        },
        {
          "dateStr": "2026-01-15",
          "time": "12:15",
          "value": 40.599998474121094
        },
        {
          "dateStr": "2026-01-15",
          "time": "12:20",
          "value": 40.650001525878906
        },
        {
          "dateStr": "2026-01-15",
          "time": "12:25",
          "value": 40.70000076293945
        },
        {
          "dateStr": "2026-01-15",
          "time": "12:30",
          "value": 40.70000076293945
        },
        {
          "dateStr": "2026-01-15",
          "time": "12:35",
          "value": 40.54999923706055
        },
        {
          "dateStr": "2026-01-15",
          "time": "12:40",
          "value": 40.599998474121094
        },
        {
          "dateStr": "2026-01-15",
          "time": "12:45",
          "value": 40.599998474121094
        },
        {
          "dateStr": "2026-01-15",
          "time": "12:50",
          "value": 40.599998474121094
        },
        {
          "dateStr": "2026-01-15",
          "time": "12:55",
          "value": 40.599998474121094
        },
        {
          "dateStr": "2026-01-15",
          "time": "13:00",
          "value": 40.599998474121094
        },
        {
          "dateStr": "2026-01-15",
          "time": "13:05",
          "value": 40.650001525878906
        },
        {
          "dateStr": "2026-01-15",
          "time": "13:10",
          "value": 40.599998474121094
        },
        {
          "dateStr": "2026-01-15",
          "time": "13:15",
          "value": 40.599998474121094
        },
        {
          "dateStr": "2026-01-15",
          "time": "13:20",
          "value": 40.599998474121094
        },
        {
          "dateStr": "2026-01-15",
          "time": "13:30",
          "value": 40.650001525878906
        }
      ]
    },
    "2887": {
      "id": "2887",
      "name": "台新新光金",
      "price": 21.6,
      "diff": 0.3500000000000014,
      "change": 1.6470588235294186,
      "isUp": true,
      "category": "民營",
      "pbPercentile": 59,
      "pbValue": 1.48,
      "data": [
        {
          "dateStr": "2026-01-15",
          "time": "09:00",
          "value": 21.350000381469727
        },
        {
          "dateStr": "2026-01-15",
          "time": "09:05",
          "value": 21.600000381469727
        },
        {
          "dateStr": "2026-01-15",
          "time": "09:10",
          "value": 21.5
        },
        {
          "dateStr": "2026-01-15",
          "time": "09:15",
          "value": 21.5
        },
        {
          "dateStr": "2026-01-15",
          "time": "09:20",
          "value": 21.5
        },
        {
          "dateStr": "2026-01-15",
          "time": "09:25",
          "value": 21.549999237060547
        },
        {
          "dateStr": "2026-01-15",
          "time": "09:30",
          "value": 21.600000381469727
        },
        {
          "dateStr": "2026-01-15",
          "time": "09:35",
          "value": 21.549999237060547
        },
        {
          "dateStr": "2026-01-15",
          "time": "09:40",
          "value": 21.600000381469727
        },
        {
          "dateStr": "2026-01-15",
          "time": "09:45",
          "value": 21.549999237060547
        },
        {
          "dateStr": "2026-01-15",
          "time": "09:50",
          "value": 21.549999237060547
        },
        {
          "dateStr": "2026-01-15",
          "time": "09:55",
          "value": 21.549999237060547
        },
        {
          "dateStr": "2026-01-15",
          "time": "10:00",
          "value": 21.600000381469727
        },
        {
          "dateStr": "2026-01-15",
          "time": "10:05",
          "value": 21.649999618530273
        },
        {
          "dateStr": "2026-01-15",
          "time": "10:10",
          "value": 21.549999237060547
        },
        {
          "dateStr": "2026-01-15",
          "time": "10:15",
          "value": 21.549999237060547
        },
        {
          "dateStr": "2026-01-15",
          "time": "10:20",
          "value": 21.549999237060547
        },
        {
          "dateStr": "2026-01-15",
          "time": "10:25",
          "value": 21.549999237060547
        },
        {
          "dateStr": "2026-01-15",
          "time": "10:30",
          "value": 21.549999237060547
        },
        {
          "dateStr": "2026-01-15",
          "time": "10:35",
          "value": 21.549999237060547
        },
        {
          "dateStr": "2026-01-15",
          "time": "10:40",
          "value": 21.600000381469727
        },
        {
          "dateStr": "2026-01-15",
          "time": "10:45",
          "value": 21.549999237060547
        },
        {
          "dateStr": "2026-01-15",
          "time": "10:50",
          "value": 21.549999237060547
        },
        {
          "dateStr": "2026-01-15",
          "time": "10:55",
          "value": 21.549999237060547
        },
        {
          "dateStr": "2026-01-15",
          "time": "11:00",
          "value": 21.549999237060547
        },
        {
          "dateStr": "2026-01-15",
          "time": "11:05",
          "value": 21.549999237060547
        },
        {
          "dateStr": "2026-01-15",
          "time": "11:10",
          "value": 21.600000381469727
        },
        {
          "dateStr": "2026-01-15",
          "time": "11:15",
          "value": 21.600000381469727
        },
        {
          "dateStr": "2026-01-15",
          "time": "11:20",
          "value": 21.600000381469727
        },
        {
          "dateStr": "2026-01-15",
          "time": "11:25",
          "value": 21.600000381469727
        },
        {
          "dateStr": "2026-01-15",
          "time": "11:30",
          "value": 21.549999237060547
        },
        {
          "dateStr": "2026-01-15",
          "time": "11:35",
          "value": 21.549999237060547
        },
        {
          "dateStr": "2026-01-15",
          "time": "11:40",
          "value": 21.600000381469727
        },
        {
          "dateStr": "2026-01-15",
          "time": "11:45",
          "value": 21.600000381469727
        },
        {
          "dateStr": "2026-01-15",
          "time": "11:50",
          "value": 21.549999237060547
        },
        {
          "dateStr": "2026-01-15",
          "time": "11:55",
          "value": 21.549999237060547
        },
        {
          "dateStr": "2026-01-15",
          "time": "12:00",
          "value": 21.549999237060547
        },
        {
          "dateStr": "2026-01-15",
          "time": "12:05",
          "value": 21.549999237060547
        },
        {
          "dateStr": "2026-01-15",
          "time": "12:10",
          "value": 21.549999237060547
        },
        {
          "dateStr": "2026-01-15",
          "time": "12:15",
          "value": 21.600000381469727
        },
        {
          "dateStr": "2026-01-15",
          "time": "12:20",
          "value": 21.600000381469727
        },
        {
          "dateStr": "2026-01-15",
          "time": "12:25",
          "value": 21.600000381469727
        },
        {
          "dateStr": "2026-01-15",
          "time": "12:30",
          "value": 21.600000381469727
        },
        {
          "dateStr": "2026-01-15",
          "time": "12:35",
          "value": 21.600000381469727
        },
        {
          "dateStr": "2026-01-15",
          "time": "12:40",
          "value": 21.600000381469727
        },
        {
          "dateStr": "2026-01-15",
          "time": "12:45",
          "value": 21.600000381469727
        },
        {
          "dateStr": "2026-01-15",
          "time": "12:50",
          "value": 21.600000381469727
        },
        {
          "dateStr": "2026-01-15",
          "time": "12:55",
          "value": 21.600000381469727
        },
        {
          "dateStr": "2026-01-15",
          "time": "13:00",
          "value": 21.600000381469727
        },
        {
          "dateStr": "2026-01-15",
          "time": "13:05",
          "value": 21.600000381469727
        },
        {
          "dateStr": "2026-01-15",
          "time": "13:10",
          "value": 21.600000381469727
        },
        {
          "dateStr": "2026-01-15",
          "time": "13:15",
          "value": 21.649999618530273
        },
        {
          "dateStr": "2026-01-15",
          "time": "13:20",
          "value": 21.649999618530273
        },
        {
          "dateStr": "2026-01-15",
          "time": "13:30",
          "value": 21.600000381469727
        }
      ]
    },
    "2889": {
      "id": "2889",
      "name": "國票金",
      "price": 16.95,
      "diff": 0,
      "change": 0,
      "isUp": true,
      "category": "民營",
      "pbPercentile": 23,
      "pbValue": 0.76,
      "data": [
        {
          "dateStr": "2026-01-15",
          "time": "09:00",
          "value": 16.950000762939453
        },
        {
          "dateStr": "2026-01-15",
          "time": "09:05",
          "value": 16.950000762939453
        },
        {
          "dateStr": "2026-01-15",
          "time": "09:10",
          "value": 16.899999618530273
        },
        {
          "dateStr": "2026-01-15",
          "time": "09:15",
          "value": 16.850000381469727
        },
        {
          "dateStr": "2026-01-15",
          "time": "09:20",
          "value": 16.649999618530273
        },
        {
          "dateStr": "2026-01-15",
          "time": "09:25",
          "value": 16.75
        },
        {
          "dateStr": "2026-01-15",
          "time": "09:30",
          "value": 16.75
        },
        {
          "dateStr": "2026-01-15",
          "time": "09:35",
          "value": 16.75
        },
        {
          "dateStr": "2026-01-15",
          "time": "09:40",
          "value": 16.850000381469727
        },
        {
          "dateStr": "2026-01-15",
          "time": "09:45",
          "value": 16.899999618530273
        },
        {
          "dateStr": "2026-01-15",
          "time": "09:50",
          "value": 16.950000762939453
        },
        {
          "dateStr": "2026-01-15",
          "time": "09:55",
          "value": 16.950000762939453
        },
        {
          "dateStr": "2026-01-15",
          "time": "10:00",
          "value": 16.950000762939453
        },
        {
          "dateStr": "2026-01-15",
          "time": "10:05",
          "value": 16.950000762939453
        },
        {
          "dateStr": "2026-01-15",
          "time": "10:10",
          "value": 16.950000762939453
        },
        {
          "dateStr": "2026-01-15",
          "time": "10:15",
          "value": 16.950000762939453
        },
        {
          "dateStr": "2026-01-15",
          "time": "10:20",
          "value": 16.950000762939453
        },
        {
          "dateStr": "2026-01-15",
          "time": "10:25",
          "value": 16.950000762939453
        },
        {
          "dateStr": "2026-01-15",
          "time": "10:30",
          "value": 16.950000762939453
        },
        {
          "dateStr": "2026-01-15",
          "time": "10:35",
          "value": 17
        },
        {
          "dateStr": "2026-01-15",
          "time": "10:40",
          "value": 17
        },
        {
          "dateStr": "2026-01-15",
          "time": "10:45",
          "value": 17
        },
        {
          "dateStr": "2026-01-15",
          "time": "10:50",
          "value": 17
        },
        {
          "dateStr": "2026-01-15",
          "time": "10:55",
          "value": 17
        },
        {
          "dateStr": "2026-01-15",
          "time": "11:00",
          "value": 17
        },
        {
          "dateStr": "2026-01-15",
          "time": "11:05",
          "value": 17
        },
        {
          "dateStr": "2026-01-15",
          "time": "11:10",
          "value": 17
        },
        {
          "dateStr": "2026-01-15",
          "time": "11:15",
          "value": 17
        },
        {
          "dateStr": "2026-01-15",
          "time": "11:20",
          "value": 17
        },
        {
          "dateStr": "2026-01-15",
          "time": "11:25",
          "value": 17
        },
        {
          "dateStr": "2026-01-15",
          "time": "11:30",
          "value": 17
        },
        {
          "dateStr": "2026-01-15",
          "time": "11:35",
          "value": 17
        },
        {
          "dateStr": "2026-01-15",
          "time": "11:40",
          "value": 17
        },
        {
          "dateStr": "2026-01-15",
          "time": "11:45",
          "value": 17
        },
        {
          "dateStr": "2026-01-15",
          "time": "11:50",
          "value": 17
        },
        {
          "dateStr": "2026-01-15",
          "time": "11:55",
          "value": 17
        },
        {
          "dateStr": "2026-01-15",
          "time": "12:00",
          "value": 17
        },
        {
          "dateStr": "2026-01-15",
          "time": "12:05",
          "value": 17
        },
        {
          "dateStr": "2026-01-15",
          "time": "12:10",
          "value": 17
        },
        {
          "dateStr": "2026-01-15",
          "time": "12:15",
          "value": 17
        },
        {
          "dateStr": "2026-01-15",
          "time": "12:20",
          "value": 17.049999237060547
        },
        {
          "dateStr": "2026-01-15",
          "time": "12:25",
          "value": 17
        },
        {
          "dateStr": "2026-01-15",
          "time": "12:30",
          "value": 17
        },
        {
          "dateStr": "2026-01-15",
          "time": "12:35",
          "value": 17
        },
        {
          "dateStr": "2026-01-15",
          "time": "12:45",
          "value": 16.950000762939453
        },
        {
          "dateStr": "2026-01-15",
          "time": "12:50",
          "value": 16.950000762939453
        },
        {
          "dateStr": "2026-01-15",
          "time": "12:55",
          "value": 16.950000762939453
        },
        {
          "dateStr": "2026-01-15",
          "time": "13:00",
          "value": 16.950000762939453
        },
        {
          "dateStr": "2026-01-15",
          "time": "13:05",
          "value": 16.950000762939453
        },
        {
          "dateStr": "2026-01-15",
          "time": "13:10",
          "value": 17
        },
        {
          "dateStr": "2026-01-15",
          "time": "13:15",
          "value": 16.950000762939453
        },
        {
          "dateStr": "2026-01-15",
          "time": "13:20",
          "value": 16.950000762939453
        },
        {
          "dateStr": "2026-01-15",
          "time": "13:30",
          "value": 16.950000762939453
        }
      ]
    },
    "2890": {
      "id": "2890",
      "name": "永豐金",
      "price": 29,
      "diff": 0.3500000000000014,
      "change": 1.2216404886562005,
      "isUp": true,
      "category": "民營",
      "pbPercentile": 58,
      "pbValue": 1.47,
      "data": [
        {
          "dateStr": "2026-01-15",
          "time": "09:00",
          "value": 28.75
        },
        {
          "dateStr": "2026-01-15",
          "time": "09:05",
          "value": 28.799999237060547
        },
        {
          "dateStr": "2026-01-15",
          "time": "09:10",
          "value": 28.950000762939453
        },
        {
          "dateStr": "2026-01-15",
          "time": "09:15",
          "value": 28.700000762939453
        },
        {
          "dateStr": "2026-01-15",
          "time": "09:20",
          "value": 28.75
        },
        {
          "dateStr": "2026-01-15",
          "time": "09:25",
          "value": 28.700000762939453
        },
        {
          "dateStr": "2026-01-15",
          "time": "09:30",
          "value": 28.799999237060547
        },
        {
          "dateStr": "2026-01-15",
          "time": "09:35",
          "value": 28.700000762939453
        },
        {
          "dateStr": "2026-01-15",
          "time": "09:40",
          "value": 28.850000381469727
        },
        {
          "dateStr": "2026-01-15",
          "time": "09:45",
          "value": 28.700000762939453
        },
        {
          "dateStr": "2026-01-15",
          "time": "09:50",
          "value": 28.700000762939453
        },
        {
          "dateStr": "2026-01-15",
          "time": "09:55",
          "value": 28.799999237060547
        },
        {
          "dateStr": "2026-01-15",
          "time": "10:00",
          "value": 28.700000762939453
        },
        {
          "dateStr": "2026-01-15",
          "time": "10:05",
          "value": 28.75
        },
        {
          "dateStr": "2026-01-15",
          "time": "10:10",
          "value": 28.700000762939453
        },
        {
          "dateStr": "2026-01-15",
          "time": "10:15",
          "value": 28.649999618530273
        },
        {
          "dateStr": "2026-01-15",
          "time": "10:20",
          "value": 28.75
        },
        {
          "dateStr": "2026-01-15",
          "time": "10:25",
          "value": 28.700000762939453
        },
        {
          "dateStr": "2026-01-15",
          "time": "10:30",
          "value": 28.799999237060547
        },
        {
          "dateStr": "2026-01-15",
          "time": "10:35",
          "value": 28.799999237060547
        },
        {
          "dateStr": "2026-01-15",
          "time": "10:40",
          "value": 28.850000381469727
        },
        {
          "dateStr": "2026-01-15",
          "time": "10:45",
          "value": 28.850000381469727
        },
        {
          "dateStr": "2026-01-15",
          "time": "10:50",
          "value": 28.850000381469727
        },
        {
          "dateStr": "2026-01-15",
          "time": "10:55",
          "value": 28.850000381469727
        },
        {
          "dateStr": "2026-01-15",
          "time": "11:00",
          "value": 28.899999618530273
        },
        {
          "dateStr": "2026-01-15",
          "time": "11:05",
          "value": 28.899999618530273
        },
        {
          "dateStr": "2026-01-15",
          "time": "11:10",
          "value": 28.950000762939453
        },
        {
          "dateStr": "2026-01-15",
          "time": "11:15",
          "value": 28.899999618530273
        },
        {
          "dateStr": "2026-01-15",
          "time": "11:20",
          "value": 28.899999618530273
        },
        {
          "dateStr": "2026-01-15",
          "time": "11:25",
          "value": 28.899999618530273
        },
        {
          "dateStr": "2026-01-15",
          "time": "11:30",
          "value": 28.899999618530273
        },
        {
          "dateStr": "2026-01-15",
          "time": "11:35",
          "value": 28.899999618530273
        },
        {
          "dateStr": "2026-01-15",
          "time": "11:40",
          "value": 28.950000762939453
        },
        {
          "dateStr": "2026-01-15",
          "time": "11:45",
          "value": 28.899999618530273
        },
        {
          "dateStr": "2026-01-15",
          "time": "11:50",
          "value": 28.950000762939453
        },
        {
          "dateStr": "2026-01-15",
          "time": "11:55",
          "value": 28.899999618530273
        },
        {
          "dateStr": "2026-01-15",
          "time": "12:00",
          "value": 28.950000762939453
        },
        {
          "dateStr": "2026-01-15",
          "time": "12:05",
          "value": 28.950000762939453
        },
        {
          "dateStr": "2026-01-15",
          "time": "12:10",
          "value": 28.950000762939453
        },
        {
          "dateStr": "2026-01-15",
          "time": "12:15",
          "value": 28.950000762939453
        },
        {
          "dateStr": "2026-01-15",
          "time": "12:20",
          "value": 29
        },
        {
          "dateStr": "2026-01-15",
          "time": "12:25",
          "value": 29
        },
        {
          "dateStr": "2026-01-15",
          "time": "12:30",
          "value": 28.950000762939453
        },
        {
          "dateStr": "2026-01-15",
          "time": "12:35",
          "value": 28.850000381469727
        },
        {
          "dateStr": "2026-01-15",
          "time": "12:40",
          "value": 28.899999618530273
        },
        {
          "dateStr": "2026-01-15",
          "time": "12:45",
          "value": 28.850000381469727
        },
        {
          "dateStr": "2026-01-15",
          "time": "12:50",
          "value": 28.899999618530273
        },
        {
          "dateStr": "2026-01-15",
          "time": "12:55",
          "value": 28.950000762939453
        },
        {
          "dateStr": "2026-01-15",
          "time": "13:00",
          "value": 28.850000381469727
        },
        {
          "dateStr": "2026-01-15",
          "time": "13:05",
          "value": 28.899999618530273
        },
        {
          "dateStr": "2026-01-15",
          "time": "13:10",
          "value": 28.850000381469727
        },
        {
          "dateStr": "2026-01-15",
          "time": "13:15",
          "value": 28.899999618530273
        },
        {
          "dateStr": "2026-01-15",
          "time": "13:20",
          "value": 29
        },
        {
          "dateStr": "2026-01-15",
          "time": "13:30",
          "value": 29
        }
      ]
    },
    "2891": {
      "id": "2891",
      "name": "中信金",
      "price": 50.4,
      "diff": 1.1000000000000014,
      "change": 2.231237322515216,
      "isUp": true,
      "category": "民營",
      "pbPercentile": 96,
      "pbValue": 2.74,
      "data": [
        {
          "dateStr": "2026-01-15",
          "time": "09:00",
          "value": 50
        },
        {
          "dateStr": "2026-01-15",
          "time": "09:05",
          "value": 50.29999923706055
        },
        {
          "dateStr": "2026-01-15",
          "time": "09:10",
          "value": 50.20000076293945
        },
        {
          "dateStr": "2026-01-15",
          "time": "09:15",
          "value": 50.20000076293945
        },
        {
          "dateStr": "2026-01-15",
          "time": "09:20",
          "value": 50.20000076293945
        },
        {
          "dateStr": "2026-01-15",
          "time": "09:25",
          "value": 50.20000076293945
        },
        {
          "dateStr": "2026-01-15",
          "time": "09:30",
          "value": 50.099998474121094
        },
        {
          "dateStr": "2026-01-15",
          "time": "09:35",
          "value": 50.20000076293945
        },
        {
          "dateStr": "2026-01-15",
          "time": "09:40",
          "value": 50.400001525878906
        },
        {
          "dateStr": "2026-01-15",
          "time": "09:45",
          "value": 50.400001525878906
        },
        {
          "dateStr": "2026-01-15",
          "time": "09:50",
          "value": 50.29999923706055
        },
        {
          "dateStr": "2026-01-15",
          "time": "09:55",
          "value": 50.29999923706055
        },
        {
          "dateStr": "2026-01-15",
          "time": "10:00",
          "value": 50.29999923706055
        },
        {
          "dateStr": "2026-01-15",
          "time": "10:05",
          "value": 50.20000076293945
        },
        {
          "dateStr": "2026-01-15",
          "time": "10:10",
          "value": 50.099998474121094
        },
        {
          "dateStr": "2026-01-15",
          "time": "10:15",
          "value": 50.099998474121094
        },
        {
          "dateStr": "2026-01-15",
          "time": "10:20",
          "value": 50.099998474121094
        },
        {
          "dateStr": "2026-01-15",
          "time": "10:25",
          "value": 50.099998474121094
        },
        {
          "dateStr": "2026-01-15",
          "time": "10:30",
          "value": 50.099998474121094
        },
        {
          "dateStr": "2026-01-15",
          "time": "10:35",
          "value": 50.099998474121094
        },
        {
          "dateStr": "2026-01-15",
          "time": "10:40",
          "value": 50.099998474121094
        },
        {
          "dateStr": "2026-01-15",
          "time": "10:45",
          "value": 50.20000076293945
        },
        {
          "dateStr": "2026-01-15",
          "time": "10:50",
          "value": 50
        },
        {
          "dateStr": "2026-01-15",
          "time": "10:55",
          "value": 50.099998474121094
        },
        {
          "dateStr": "2026-01-15",
          "time": "11:00",
          "value": 50
        },
        {
          "dateStr": "2026-01-15",
          "time": "11:05",
          "value": 50
        },
        {
          "dateStr": "2026-01-15",
          "time": "11:10",
          "value": 50.20000076293945
        },
        {
          "dateStr": "2026-01-15",
          "time": "11:15",
          "value": 50.20000076293945
        },
        {
          "dateStr": "2026-01-15",
          "time": "11:20",
          "value": 50.20000076293945
        },
        {
          "dateStr": "2026-01-15",
          "time": "11:25",
          "value": 50.20000076293945
        },
        {
          "dateStr": "2026-01-15",
          "time": "11:30",
          "value": 50.20000076293945
        },
        {
          "dateStr": "2026-01-15",
          "time": "11:35",
          "value": 50.20000076293945
        },
        {
          "dateStr": "2026-01-15",
          "time": "11:40",
          "value": 50.29999923706055
        },
        {
          "dateStr": "2026-01-15",
          "time": "11:45",
          "value": 50.29999923706055
        },
        {
          "dateStr": "2026-01-15",
          "time": "11:50",
          "value": 50.29999923706055
        },
        {
          "dateStr": "2026-01-15",
          "time": "11:55",
          "value": 50.29999923706055
        },
        {
          "dateStr": "2026-01-15",
          "time": "12:00",
          "value": 50.29999923706055
        },
        {
          "dateStr": "2026-01-15",
          "time": "12:05",
          "value": 50.400001525878906
        },
        {
          "dateStr": "2026-01-15",
          "time": "12:10",
          "value": 50.29999923706055
        },
        {
          "dateStr": "2026-01-15",
          "time": "12:15",
          "value": 50.20000076293945
        },
        {
          "dateStr": "2026-01-15",
          "time": "12:20",
          "value": 50.20000076293945
        },
        {
          "dateStr": "2026-01-15",
          "time": "12:25",
          "value": 50.29999923706055
        },
        {
          "dateStr": "2026-01-15",
          "time": "12:30",
          "value": 50.29999923706055
        },
        {
          "dateStr": "2026-01-15",
          "time": "12:35",
          "value": 50.29999923706055
        },
        {
          "dateStr": "2026-01-15",
          "time": "12:40",
          "value": 50.20000076293945
        },
        {
          "dateStr": "2026-01-15",
          "time": "12:45",
          "value": 50.099998474121094
        },
        {
          "dateStr": "2026-01-15",
          "time": "12:50",
          "value": 50.29999923706055
        },
        {
          "dateStr": "2026-01-15",
          "time": "12:55",
          "value": 50.20000076293945
        },
        {
          "dateStr": "2026-01-15",
          "time": "13:00",
          "value": 50.20000076293945
        },
        {
          "dateStr": "2026-01-15",
          "time": "13:05",
          "value": 50.20000076293945
        },
        {
          "dateStr": "2026-01-15",
          "time": "13:10",
          "value": 50.20000076293945
        },
        {
          "dateStr": "2026-01-15",
          "time": "13:15",
          "value": 50.20000076293945
        },
        {
          "dateStr": "2026-01-15",
          "time": "13:20",
          "value": 50.29999923706055
        },
        {
          "dateStr": "2026-01-15",
          "time": "13:30",
          "value": 50.400001525878906
        }
      ]
    },
    "2892": {
      "id": "2892",
      "name": "第一金",
      "price": 29.8,
      "diff": 0.40000000000000213,
      "change": 1.3605442176870821,
      "isUp": true,
      "category": "官股",
      "pbPercentile": 94,
      "pbValue": 2.59,
      "data": [
        {
          "dateStr": "2026-01-15",
          "time": "09:00",
          "value": 29.600000381469727
        },
        {
          "dateStr": "2026-01-15",
          "time": "09:05",
          "value": 29.649999618530273
        },
        {
          "dateStr": "2026-01-15",
          "time": "09:10",
          "value": 29.75
        },
        {
          "dateStr": "2026-01-15",
          "time": "09:15",
          "value": 29.700000762939453
        },
        {
          "dateStr": "2026-01-15",
          "time": "09:20",
          "value": 29.700000762939453
        },
        {
          "dateStr": "2026-01-15",
          "time": "09:25",
          "value": 29.700000762939453
        },
        {
          "dateStr": "2026-01-15",
          "time": "09:30",
          "value": 29.649999618530273
        },
        {
          "dateStr": "2026-01-15",
          "time": "09:35",
          "value": 29.700000762939453
        },
        {
          "dateStr": "2026-01-15",
          "time": "09:40",
          "value": 29.75
        },
        {
          "dateStr": "2026-01-15",
          "time": "09:45",
          "value": 29.700000762939453
        },
        {
          "dateStr": "2026-01-15",
          "time": "09:50",
          "value": 29.700000762939453
        },
        {
          "dateStr": "2026-01-15",
          "time": "09:55",
          "value": 29.700000762939453
        },
        {
          "dateStr": "2026-01-15",
          "time": "10:00",
          "value": 29.75
        },
        {
          "dateStr": "2026-01-15",
          "time": "10:05",
          "value": 29.75
        },
        {
          "dateStr": "2026-01-15",
          "time": "10:10",
          "value": 29.700000762939453
        },
        {
          "dateStr": "2026-01-15",
          "time": "10:15",
          "value": 29.700000762939453
        },
        {
          "dateStr": "2026-01-15",
          "time": "10:20",
          "value": 29.700000762939453
        },
        {
          "dateStr": "2026-01-15",
          "time": "10:25",
          "value": 29.700000762939453
        },
        {
          "dateStr": "2026-01-15",
          "time": "10:30",
          "value": 29.700000762939453
        },
        {
          "dateStr": "2026-01-15",
          "time": "10:35",
          "value": 29.700000762939453
        },
        {
          "dateStr": "2026-01-15",
          "time": "10:40",
          "value": 29.700000762939453
        },
        {
          "dateStr": "2026-01-15",
          "time": "10:45",
          "value": 29.75
        },
        {
          "dateStr": "2026-01-15",
          "time": "10:50",
          "value": 29.75
        },
        {
          "dateStr": "2026-01-15",
          "time": "10:55",
          "value": 29.700000762939453
        },
        {
          "dateStr": "2026-01-15",
          "time": "11:00",
          "value": 29.75
        },
        {
          "dateStr": "2026-01-15",
          "time": "11:05",
          "value": 29.75
        },
        {
          "dateStr": "2026-01-15",
          "time": "11:10",
          "value": 29.75
        },
        {
          "dateStr": "2026-01-15",
          "time": "11:15",
          "value": 29.75
        },
        {
          "dateStr": "2026-01-15",
          "time": "11:20",
          "value": 29.799999237060547
        },
        {
          "dateStr": "2026-01-15",
          "time": "11:25",
          "value": 29.850000381469727
        },
        {
          "dateStr": "2026-01-15",
          "time": "11:30",
          "value": 29.850000381469727
        },
        {
          "dateStr": "2026-01-15",
          "time": "11:35",
          "value": 29.850000381469727
        },
        {
          "dateStr": "2026-01-15",
          "time": "11:40",
          "value": 29.850000381469727
        },
        {
          "dateStr": "2026-01-15",
          "time": "11:45",
          "value": 29.799999237060547
        },
        {
          "dateStr": "2026-01-15",
          "time": "11:50",
          "value": 29.850000381469727
        },
        {
          "dateStr": "2026-01-15",
          "time": "11:55",
          "value": 29.850000381469727
        },
        {
          "dateStr": "2026-01-15",
          "time": "12:00",
          "value": 29.799999237060547
        },
        {
          "dateStr": "2026-01-15",
          "time": "12:05",
          "value": 29.700000762939453
        },
        {
          "dateStr": "2026-01-15",
          "time": "12:10",
          "value": 29.799999237060547
        },
        {
          "dateStr": "2026-01-15",
          "time": "12:15",
          "value": 29.75
        },
        {
          "dateStr": "2026-01-15",
          "time": "12:20",
          "value": 29.700000762939453
        },
        {
          "dateStr": "2026-01-15",
          "time": "12:25",
          "value": 29.799999237060547
        },
        {
          "dateStr": "2026-01-15",
          "time": "12:30",
          "value": 29.75
        },
        {
          "dateStr": "2026-01-15",
          "time": "12:35",
          "value": 29.700000762939453
        },
        {
          "dateStr": "2026-01-15",
          "time": "12:40",
          "value": 29.700000762939453
        },
        {
          "dateStr": "2026-01-15",
          "time": "12:45",
          "value": 29.649999618530273
        },
        {
          "dateStr": "2026-01-15",
          "time": "12:50",
          "value": 29.700000762939453
        },
        {
          "dateStr": "2026-01-15",
          "time": "12:55",
          "value": 29.75
        },
        {
          "dateStr": "2026-01-15",
          "time": "13:00",
          "value": 29.75
        },
        {
          "dateStr": "2026-01-15",
          "time": "13:05",
          "value": 29.75
        },
        {
          "dateStr": "2026-01-15",
          "time": "13:10",
          "value": 29.75
        },
        {
          "dateStr": "2026-01-15",
          "time": "13:15",
          "value": 29.75
        },
        {
          "dateStr": "2026-01-15",
          "time": "13:20",
          "value": 29.700000762939453
        },
        {
          "dateStr": "2026-01-15",
          "time": "13:30",
          "value": 29.799999237060547
        }
      ]
    },
    "5880": {
      "id": "5880",
      "name": "合庫金",
      "price": 24.05,
      "diff": 0.10000000000000142,
      "change": 0.41753653444677,
      "isUp": true,
      "category": "官股",
      "pbPercentile": 16,
      "pbValue": 0.53,
      "data": [
        {
          "dateStr": "2026-01-15",
          "time": "09:00",
          "value": 24
        },
        {
          "dateStr": "2026-01-15",
          "time": "09:05",
          "value": 24
        },
        {
          "dateStr": "2026-01-15",
          "time": "09:10",
          "value": 24
        },
        {
          "dateStr": "2026-01-15",
          "time": "09:15",
          "value": 24
        },
        {
          "dateStr": "2026-01-15",
          "time": "09:20",
          "value": 24
        },
        {
          "dateStr": "2026-01-15",
          "time": "09:25",
          "value": 23.950000762939453
        },
        {
          "dateStr": "2026-01-15",
          "time": "09:30",
          "value": 23.950000762939453
        },
        {
          "dateStr": "2026-01-15",
          "time": "09:35",
          "value": 24
        },
        {
          "dateStr": "2026-01-15",
          "time": "09:40",
          "value": 24.049999237060547
        },
        {
          "dateStr": "2026-01-15",
          "time": "09:45",
          "value": 24.049999237060547
        },
        {
          "dateStr": "2026-01-15",
          "time": "09:50",
          "value": 24
        },
        {
          "dateStr": "2026-01-15",
          "time": "09:55",
          "value": 24.049999237060547
        },
        {
          "dateStr": "2026-01-15",
          "time": "10:00",
          "value": 24.049999237060547
        },
        {
          "dateStr": "2026-01-15",
          "time": "10:05",
          "value": 24
        },
        {
          "dateStr": "2026-01-15",
          "time": "10:10",
          "value": 24
        },
        {
          "dateStr": "2026-01-15",
          "time": "10:15",
          "value": 24
        },
        {
          "dateStr": "2026-01-15",
          "time": "10:20",
          "value": 24
        },
        {
          "dateStr": "2026-01-15",
          "time": "10:25",
          "value": 24
        },
        {
          "dateStr": "2026-01-15",
          "time": "10:30",
          "value": 24
        },
        {
          "dateStr": "2026-01-15",
          "time": "10:35",
          "value": 23.950000762939453
        },
        {
          "dateStr": "2026-01-15",
          "time": "10:40",
          "value": 24
        },
        {
          "dateStr": "2026-01-15",
          "time": "10:45",
          "value": 24
        },
        {
          "dateStr": "2026-01-15",
          "time": "10:50",
          "value": 23.950000762939453
        },
        {
          "dateStr": "2026-01-15",
          "time": "10:55",
          "value": 24
        },
        {
          "dateStr": "2026-01-15",
          "time": "11:00",
          "value": 24
        },
        {
          "dateStr": "2026-01-15",
          "time": "11:05",
          "value": 23.950000762939453
        },
        {
          "dateStr": "2026-01-15",
          "time": "11:10",
          "value": 23.950000762939453
        },
        {
          "dateStr": "2026-01-15",
          "time": "11:15",
          "value": 24
        },
        {
          "dateStr": "2026-01-15",
          "time": "11:20",
          "value": 24
        },
        {
          "dateStr": "2026-01-15",
          "time": "11:25",
          "value": 24
        },
        {
          "dateStr": "2026-01-15",
          "time": "11:30",
          "value": 23.950000762939453
        },
        {
          "dateStr": "2026-01-15",
          "time": "11:35",
          "value": 24
        },
        {
          "dateStr": "2026-01-15",
          "time": "11:40",
          "value": 24
        },
        {
          "dateStr": "2026-01-15",
          "time": "11:45",
          "value": 24
        },
        {
          "dateStr": "2026-01-15",
          "time": "11:50",
          "value": 24
        },
        {
          "dateStr": "2026-01-15",
          "time": "11:55",
          "value": 24
        },
        {
          "dateStr": "2026-01-15",
          "time": "12:00",
          "value": 24
        },
        {
          "dateStr": "2026-01-15",
          "time": "12:05",
          "value": 24
        },
        {
          "dateStr": "2026-01-15",
          "time": "12:10",
          "value": 24
        },
        {
          "dateStr": "2026-01-15",
          "time": "12:15",
          "value": 24
        },
        {
          "dateStr": "2026-01-15",
          "time": "12:20",
          "value": 23.950000762939453
        },
        {
          "dateStr": "2026-01-15",
          "time": "12:25",
          "value": 24
        },
        {
          "dateStr": "2026-01-15",
          "time": "12:30",
          "value": 24.049999237060547
        },
        {
          "dateStr": "2026-01-15",
          "time": "12:35",
          "value": 24
        },
        {
          "dateStr": "2026-01-15",
          "time": "12:40",
          "value": 24.049999237060547
        },
        {
          "dateStr": "2026-01-15",
          "time": "12:45",
          "value": 24
        },
        {
          "dateStr": "2026-01-15",
          "time": "12:50",
          "value": 24
        },
        {
          "dateStr": "2026-01-15",
          "time": "12:55",
          "value": 24
        },
        {
          "dateStr": "2026-01-15",
          "time": "13:00",
          "value": 24
        },
        {
          "dateStr": "2026-01-15",
          "time": "13:05",
          "value": 24
        },
        {
          "dateStr": "2026-01-15",
          "time": "13:10",
          "value": 24
        },
        {
          "dateStr": "2026-01-15",
          "time": "13:15",
          "value": 24
        },
        {
          "dateStr": "2026-01-15",
          "time": "13:20",
          "value": 24.049999237060547
        },
        {
          "dateStr": "2026-01-15",
          "time": "13:30",
          "value": 24.049999237060547
        }
      ]
    }
  }
}